github_maintainer/__init__.py
github_maintainer/__main__.py
github_maintainer/cli.py
github_maintainer-0.1.8.dist-info/DESCRIPTION.rst
github_maintainer-0.1.8.dist-info/METADATA
github_maintainer-0.1.8.dist-info/RECORD
github_maintainer-0.1.8.dist-info/WHEEL
github_maintainer-0.1.8.dist-info/entry_points.txt
github_maintainer-0.1.8.dist-info/metadata.json
github_maintainer-0.1.8.dist-info/top_level.txt
