Metadata-Version: 2.0
Name: github-maintainer
Version: 0.1.8
Summary: CLI support tool for GitHub repo maintainers
Home-page: https://github.com/zalando-stups/github-maintainer-cli
Author: Henning Jacobs
Author-email: henning.jacobs@zalando.de
License: Apache License 2.0
Keywords: github git project maintainer
Platform: UNKNOWN
Classifier: Development Status :: 4 - Beta
Classifier: Environment :: Console
Classifier: Intended Audience :: Developers
Classifier: License :: OSI Approved :: Apache Software License
Classifier: Operating System :: POSIX :: Linux
Classifier: Programming Language :: Python
Classifier: Programming Language :: Python :: 3.4
Classifier: Programming Language :: Python :: Implementation :: CPython
Requires-Dist: clickclick
Requires-Dist: requests
Requires-Dist: stups-cli-support
